MANIFEST.in
README.rst
setup.py
collective/__init__.py
collective.geo.wms.egg-info/PKG-INFO
collective.geo.wms.egg-info/SOURCES.txt
collective.geo.wms.egg-info/dependency_links.txt
collective.geo.wms.egg-info/entry_points.txt
collective.geo.wms.egg-info/namespace_packages.txt
collective.geo.wms.egg-info/not-zip-safe
collective.geo.wms.egg-info/requires.txt
collective.geo.wms.egg-info/top_level.txt
collective/geo/__init__.py
collective/geo/wms/INTEGRATION.txt
collective/geo/wms/__init__.py
collective/geo/wms/configure.zcml
collective/geo/wms/interfaces.py
collective/geo/wms/maplayers.py
collective/geo/wms/tests.py
collective/geo/wms/version.txt
collective/geo/wms/views.py
collective/geo/wms/wmslayer.py
collective/geo/wms/wmsserver.py
collective/geo/wms/locales/README.txt
collective/geo/wms/profiles/default/metadata.xml
collective/geo/wms/profiles/default/types.xml
collective/geo/wms/profiles/default/types/collective.geo.wms.wmslayer.xml
collective/geo/wms/profiles/default/types/collective.geo.wms.wmsserver.xml
collective/geo/wms/static/README.txt
collective/geo/wms/static/layers.png
collective/geo/wms/static/map_server.png
collective/geo/wms/wmslayer_templates/view.pt
collective/geo/wms/wmsserver_templates/view.pt
docs/HISTORY.txt
docs/INSTALL.txt
docs/LICENSE.GPL
docs/LICENSE.txt