Metadata-Version: 1.0
Name: collective.geo.wms
Version: 0.2
Summary: WMS Support for Collective Geo
Home-page: https://github.com/collective/collective.geo.wms
Author: Christian Ledermann
Author-email: christian.ledermann@gmail.com
License: GPL
Keywords: GIS WMS WMTS Openlayers Dexterity
Platform: UNKNOWN
Classifier: Framework :: Plone
Classifier: Framework :: Plone :: 4.0
Classifier: Framework :: Plone :: 4.1
Classifier: Framework :: Plone :: 4.2
Classifier: Programming Language :: Python
Classifier: Topic :: Scientific/Engineering :: GIS
Classifier: License :: OSI Approved :: GNU General Public License (GPL)
Classifier: Development Status :: 4 - Beta
Classifier: Operating System :: OS Independent
